flask_pay_paypal/__init__.py
flask_pay_paypal-0.0.7.dist-info/METADATA
flask_pay_paypal-0.0.7.dist-info/WHEEL
flask_pay_paypal-0.0.7.dist-info/top_level.txt
flask_pay_paypal-0.0.7.dist-info/RECORD
