Metadata-Version: 2.1
Name: flask-pay-paypal
Version: 0.0.7
Summary: A simple PayPal integration for Flask
Maintainer-email: 浩 <pythonnic@qq.com>
Requires-Python: >=3.6
Requires-Dist: requests
Requires-Dist: python-dotenv
Provides-Extra: async
Requires-Dist: asgiref >=3.2 ; extra == 'async'
Provides-Extra: dotenv
Requires-Dist: python-dotenv ; extra == 'dotenv'
